spherimatch/__init__.py
spherimatch/catalog.py
spherimatch/chunk.py
spherimatch/chunk_generator.py
spherimatch/chunk_generator_grid.py
spherimatch/disjoint_set.py
spherimatch/euclidean_vs_angular_distance_local.py
spherimatch/fof.py
spherimatch/result_fof.py
spherimatch/result_xmatch.py
spherimatch/utilities_spherical.py
spherimatch/xmatch.py
spherimatch-0.1.dist-info/METADATA
spherimatch-0.1.dist-info/WHEEL
spherimatch-0.1.dist-info/licenses/LICENSE.txt
spherimatch-0.1.dist-info/RECORD
