Metadata-Version: 2.4
Name: spherimatch
Version: 0.1
Summary: Cross-Matching and Self-Matching in Spherical Coordinates.
Project-URL: Homepage, https://github.com/technic960183/spherimatch/
Project-URL: Documentation, https://technic960183.github.io/spherimatch/
Project-URL: Repository, https://github.com/technic960183/spherimatch.git
Project-URL: Bug Tracker, https://github.com/technic960183/spherimatch/issues
Author: Yuan-Ming Hsu
License: MIT License
License-File: LICENSE.txt
Keywords: astronomy,cross-matching,spherical
Classifier: Development Status :: 4 - Beta
Classifier: License :: OSI Approved :: MIT License
Classifier: Programming Language :: Python :: 3
Requires-Python: >=3.9
Requires-Dist: numpy
Requires-Dist: pandas
Requires-Dist: scipy
Provides-Extra: dev
Requires-Dist: build; extra == 'dev'
Requires-Dist: sphinx; extra == 'dev'
Requires-Dist: sphinx-rtd-theme; extra == 'dev'
